<?xml version="1.0" encoding="utf-8" ?>
<c2eventsheet>
    <!--All the 'name' attributes are ignored by Construct 2 - they are there for readability only.-->
    <name>LevelCommon</name>
    <events>
        <variable constant="1" name="WINDOW_WIDTH" sid="1295065130285739" static="0" type="number">980</variable>
        <variable constant="1" name="WINDOW_HEIGHT" sid="8561640085275173" static="0" type="number">500</variable>
        <include>QuestCommon</include>
        <include>LevelControls</include>
        <include>LevelRecording</include>
        <include>LevelPlayback</include>
        <include>LevelFade</include>
        <include>LevelStartFinish</include>
        <include>LevelInput</include>
        <include>FoxySimpleSCMLSpritesBinding</include>
        <event-block sid="5391175458694452">
            <conditions>
                <condition id="-3" name="On end of layout" sid="9603448931859444" type="System" />
            </conditions>
            <actions>
                <action id="0" name="Call function" sid="7109870308187546" type="Function">
                    <param id="0" name="Name">&quot;VarsReset&quot;</param>
                    <param id="1" name="Parameter {n}"></param>
                </action>
            </actions>
        </event-block>
    </events>
</c2eventsheet>
